git2wp/__init__.py
git2wp/__main__.py
git2wp-0.1.0.dist-info/METADATA
git2wp-0.1.0.dist-info/WHEEL
git2wp-0.1.0.dist-info/entry_points.txt
git2wp-0.1.0.dist-info/RECORD
